spleenseg
spleenseg/comms
spleenseg/core
spleenseg/models
spleenseg/plotting
spleenseg/transforms
