Metadata-Version: 2.1
Name: spleenseg
Version: 1.2.34
Summary: A ChRIS DS plugin heavily hacked off project MONAI's spleen segmenation notebook
Home-page: https://github.com/FNNDSC/pl-monai_spleenseg
Author: FNNDSC
Author-email: dev@babyMRI.org
License: MIT
Classifier: License :: OSI Approved :: MIT License
Classifier: Topic :: Scientific/Engineering
Classifier: Topic :: Scientific/Engineering :: Bio-Informatics
Classifier: Topic :: Scientific/Engineering :: Medical Science Apps.
License-File: LICENSE
Requires-Dist: chris_plugin==0.4.0
Requires-Dist: pudb
Requires-Dist: pyfiglet
Requires-Dist: matplotlib
Requires-Dist: monai-weekly
Requires-Dist: gdown
Requires-Dist: nibabel
Requires-Dist: tqdm
Requires-Dist: ignite
Requires-Dist: scikit-build
Requires-Dist: torch
Requires-Dist: pytorch-ignite
Requires-Dist: scikit-image
Requires-Dist: scipy
Requires-Dist: pillow
Requires-Dist: tensorboard
Requires-Dist: torchvision
Requires-Dist: psutil
Requires-Dist: pandas
Requires-Dist: einops
Requires-Dist: transformers
Requires-Dist: mlflow
Requires-Dist: pynrrd
Requires-Dist: clearml
Provides-Extra: none
Provides-Extra: dev
Requires-Dist: pytest~=7.1; extra == "dev"
